{
    "cameraId": "CAM01",
    "tools": {
        "geometries": {
            "arcs": [
                {
                    "coordinateSpace": "part",
                    "edgeCleanupDerivative": 12,
                    "edgeSensitivity": 159,
                    "edgeStatisticalFilter": 0,
                    "enabled": true,
                    "endAngleRadians": 0.05643170143459245,
                    "id": "arc_2",
                    "imageCenter": {
                        "x": 817.5437213636717,
                        "y": 439.56787295177446
                    },
                    "imageEnd": {
                        "x": 896,
                        "y": 444
                    },
                    "imageStart": {
                        "x": 739,
                        "y": 442
                    },
                    "imageThrough": {
                        "x": 818.5446766861718,
                        "y": 360.9928801355154
                    },
                    "innerBand": 20,
                    "outerBand": 20,
                    "partCenter": {
                        "x": -90.52028691950314,
                        "y": 1.566092665581718
                    },
                    "partEnd": {
                        "x": -88.05458511874578,
                        "y": -76.9765818640174
                    },
                    "partEndAngleRadians": 4.743771821453856,
                    "partStart": {
                        "x": -86.1216978719396,
                        "y": 80.02425872892697
                    },
                    "partStartAngleRadians": 1.5147920939750068,
                    "partThrough": {
                        "x": -169.09570043375305,
                        "y": 2.5334595543233664
                    },
                    "pickMode": "first",
                    "radius": 78.5813680692364,
                    "scanDirection": "normal_positive",
                    "startAngleRadians": 3.1106372811353293,
                    "transition": "dark_to_light",
                    "type": "edge_arc",
                    "useSubpixel": true
                },
                {
                    "coordinateSpace": "part",
                    "edgeCleanupDerivative": 12,
                    "edgeSensitivity": 130,
                    "edgeStatisticalFilter": 0,
                    "enabled": true,
                    "endAngleRadians": 3.704318101161872,
                    "id": "arc_3",
                    "imageCenter": {
                        "x": 826.1592541116516,
                        "y": 610.2991660875608
                    },
                    "imageEnd": {
                        "x": 748,
                        "y": 561
                    },
                    "imageStart": {
                        "x": 787,
                        "y": 694
                    },
                    "imageThrough": {
                        "x": 737.4848040545166,
                        "y": 636.3014484351418
                    },
                    "innerBand": 20,
                    "outerBand": 20,
                    "partCenter": {
                        "x": 80.09507249787495,
                        "y": -9.46866913163079
                    },
                    "partEnd": {
                        "x": 30.979186234794536,
                        "y": 68.80588929453211
                    },
                    "partEndAngleRadians": 2.1311785502564606,
                    "partStart": {
                        "x": 163.88743544678118,
                        "y": 29.49434784161456
                    },
                    "partStartAngleRadians": 0.43525343581277137,
                    "partThrough": {
                        "x": 106.30506737934662,
                        "y": 79.1446083640802
                    },
                    "pickMode": "first",
                    "radius": 92.40820732066304,
                    "scanDirection": "normal_positive",
                    "startAngleRadians": 2.008392986718183,
                    "transition": "dark_to_light",
                    "type": "edge_arc",
                    "useSubpixel": true
                },
                {
                    "coordinateSpace": "part",
                    "edgeCleanupDerivative": 12,
                    "edgeSensitivity": 157,
                    "edgeStatisticalFilter": 0,
                    "enabled": true,
                    "endAngleRadians": 1.1719481886243606,
                    "id": "arc_4",
                    "imageCenter": {
                        "x": 811.4223424570338,
                        "y": 610.9527901548907
                    },
                    "imageEnd": {
                        "x": 846,
                        "y": 693
                    },
                    "imageStart": {
                        "x": 883,
                        "y": 558
                    },
                    "imageThrough": {
                        "x": 897.2913574173115,
                        "y": 634.4872609217816
                    },
                    "innerBand": 20,
                    "outerBand": 20,
                    "partCenter": {
                        "x": 80.78322662588205,
                        "y": 5.266670478758641
                    },
                    "partEnd": {
                        "x": 162.7491880961242,
                        "y": -29.503146960866015
                    },
                    "partEndAngleRadians": 5.881993944898535,
                    "partStart": {
                        "x": 27.662859505403635,
                        "y": -66.18671041754072
                    },
                    "partStartAngleRadians": 4.073107930303928,
                    "partThrough": {
                        "x": 104.11642262038198,
                        "y": -80.65725523002337
                    },
                    "pickMode": "first",
                    "radius": 89.03571780204865,
                    "scanDirection": "normal_positive",
                    "startAngleRadians": 5.64624748120934,
                    "transition": "dark_to_light",
                    "type": "edge_arc",
                    "useSubpixel": true
                },
                {
                    "coordinateSpace": "part",
                    "edgeCleanupDerivative": 12,
                    "edgeSensitivity": 60,
                    "edgeStatisticalFilter": 0,
                    "enabled": true,
                    "endAngleRadians": 3.431416910064961,
                    "id": "arc_5",
                    "imageCenter": {
                        "x": 1086.26,
                        "y": 532.7218181818182
                    },
                    "imageEnd": {
                        "x": 886,
                        "y": 473
                    },
                    "imageStart": {
                        "x": 878,
                        "y": 550
                    },
                    "imageThrough": {
                        "x": 878.4033243795138,
                        "y": 511.12631941605343
                    },
                    "innerBand": 20,
                    "outerBand": 20,
                    "partCenter": {
                        "x": 0.746349687026463,
                        "y": -269.2906358680879
                    },
                    "partEnd": {
                        "x": -57.676333450898184,
                        "y": -68.64778585367102
                    },
                    "partEndAngleRadians": 1.8541395592689958,
                    "partStart": {
                        "x": 19.37389724242659,
                        "y": -61.14698922228361
                    },
                    "partStartAngleRadians": 1.4815403953397486,
                    "partThrough": {
                        "x": -19.501580862395954,
                        "y": -61.298365638139444
                    },
                    "pickMode": "first",
                    "radius": 208.97550853375654,
                    "scanDirection": "normal_positive",
                    "startAngleRadians": 3.058817746135714,
                    "transition": "light_to_dark",
                    "type": "edge_arc",
                    "useSubpixel": true
                },
                {
                    "coordinateSpace": "part",
                    "edgeCleanupDerivative": 12,
                    "edgeSensitivity": 60,
                    "edgeStatisticalFilter": 0,
                    "enabled": true,
                    "endAngleRadians": 0.18385795116398146,
                    "id": "arc_6",
                    "imageCenter": {
                        "x": 600.65,
                        "y": 521.4833333333333
                    },
                    "imageEnd": {
                        "x": 754,
                        "y": 550
                    },
                    "imageStart": {
                        "x": 744,
                        "y": 460
                    },
                    "imageThrough": {
                        "x": 755.6749092887978,
                        "y": 504.2583434123557
                    },
                    "innerBand": 20,
                    "outerBand": 20,
                    "partCenter": {
                        "x": -7.344671100939614,
                        "y": 216.38200184614269
                    },
                    "partEnd": {
                        "x": 20.177538592550267,
                        "y": 62.85040655916162
                    },
                    "partEndAngleRadians": 4.889765907547602,
                    "partStart": {
                        "x": -69.75576146252098,
                        "y": 73.4334846182389
                    },
                    "partStartAngleRadians": 4.300735562871848,
                    "partThrough": {
                        "x": -25.574012390992184,
                        "y": 61.47198314525762
                    },
                    "pickMode": "first",
                    "radius": 155.97891773498682,
                    "scanDirection": "normal_positive",
                    "startAngleRadians": 5.878012913667813,
                    "transition": "light_to_dark",
                    "type": "edge_arc",
                    "useSubpixel": true
                }
            ],
            "enabled": true,
            "guideReferenceSize": {
                "height": 1216,
                "width": 1936
            }
        },
        "measurements": {
            "enabled": true,
            "items": [
                {
                    "criterion": "average",
                    "enabled": true,
                    "hasMax": false,
                    "hasMin": false,
                    "hasNominal": false,
                    "hasSampleScale": false,
                    "id": "measurement_1",
                    "max": 0,
                    "min": 0,
                    "nominal": 0,
                    "samplePixels": 178.66132540224305,
                    "sampleValue": 0,
                    "sourceAId": "arc_4",
                    "type": "circle_diameter",
                    "unit": "px"
                },
                {
                    "criterion": "average",
                    "enabled": true,
                    "hasMax": false,
                    "hasMin": false,
                    "hasNominal": false,
                    "hasSampleScale": false,
                    "id": "measurement_2",
                    "max": 0,
                    "min": 0,
                    "nominal": 0,
                    "samplePixels": 179.3372103978446,
                    "sampleValue": 0,
                    "sourceAId": "arc_3",
                    "type": "circle_diameter",
                    "unit": "px"
                },
                {
                    "criterion": "average",
                    "enabled": true,
                    "hasMax": false,
                    "hasMin": false,
                    "hasNominal": false,
                    "hasSampleScale": false,
                    "id": "measurement_3",
                    "max": 0,
                    "min": 0,
                    "nominal": 0,
                    "samplePixels": 156.50930084559388,
                    "sampleValue": 0,
                    "sourceAId": "arc_2",
                    "type": "circle_diameter",
                    "unit": "px"
                }
            ]
        },
        "surfaceLocalization": {
            "aoes": {
                "model": {
                    "id": "model",
                    "label": "model",
                    "searchRoi": {
                        "height": 368,
                        "width": 207,
                        "x": 714,
                        "y": 350
                    }
                }
            },
            "enabled": true,
            "exclusionRects": [
            ],
            "method": "model",
            "model": {
                "angleRange": {
                    "end": 180,
                    "start": -180,
                    "step": 1
                },
                "contour": [
                    {
                        "x": 806,
                        "y": 360
                    },
                    {
                        "x": 805,
                        "y": 361
                    },
                    {
                        "x": 801,
                        "y": 361
                    },
                    {
                        "x": 800,
                        "y": 362
                    },
                    {
                        "x": 798,
                        "y": 362
                    },
                    {
                        "x": 797,
                        "y": 363
                    },
                    {
                        "x": 794,
                        "y": 363
                    },
                    {
                        "x": 793,
                        "y": 364
                    },
                    {
                        "x": 790,
                        "y": 364
                    },
                    {
                        "x": 789,
                        "y": 365
                    },
                    {
                        "x": 786,
                        "y": 365
                    },
                    {
                        "x": 785,
                        "y": 366
                    },
                    {
                        "x": 782,
                        "y": 366
                    },
                    {
                        "x": 780,
                        "y": 368
                    },
                    {
                        "x": 779,
                        "y": 368
                    },
                    {
                        "x": 778,
                        "y": 369
                    },
                    {
                        "x": 777,
                        "y": 369
                    },
                    {
                        "x": 776,
                        "y": 370
                    },
                    {
                        "x": 775,
                        "y": 370
                    },
                    {
                        "x": 774,
                        "y": 371
                    },
                    {
                        "x": 773,
                        "y": 371
                    },
                    {
                        "x": 772,
                        "y": 372
                    },
                    {
                        "x": 771,
                        "y": 372
                    },
                    {
                        "x": 769,
                        "y": 374
                    },
                    {
                        "x": 768,
                        "y": 374
                    },
                    {
                        "x": 767,
                        "y": 375
                    },
                    {
                        "x": 766,
                        "y": 375
                    },
                    {
                        "x": 757,
                        "y": 384
                    },
                    {
                        "x": 756,
                        "y": 384
                    },
                    {
                        "x": 755,
                        "y": 385
                    },
                    {
                        "x": 755,
                        "y": 386
                    },
                    {
                        "x": 751,
                        "y": 390
                    },
                    {
                        "x": 751,
                        "y": 391
                    },
                    {
                        "x": 750,
                        "y": 392
                    },
                    {
                        "x": 750,
                        "y": 393
                    },
                    {
                        "x": 749,
                        "y": 394
                    },
                    {
                        "x": 749,
                        "y": 395
                    },
                    {
                        "x": 748,
                        "y": 396
                    },
                    {
                        "x": 748,
                        "y": 397
                    },
                    {
                        "x": 747,
                        "y": 398
                    },
                    {
                        "x": 747,
                        "y": 399
                    },
                    {
                        "x": 746,
                        "y": 400
                    },
                    {
                        "x": 746,
                        "y": 402
                    },
                    {
                        "x": 745,
                        "y": 403
                    },
                    {
                        "x": 745,
                        "y": 404
                    },
                    {
                        "x": 744,
                        "y": 405
                    },
                    {
                        "x": 744,
                        "y": 406
                    },
                    {
                        "x": 743,
                        "y": 407
                    },
                    {
                        "x": 743,
                        "y": 409
                    },
                    {
                        "x": 742,
                        "y": 410
                    },
                    {
                        "x": 742,
                        "y": 412
                    },
                    {
                        "x": 741,
                        "y": 413
                    },
                    {
                        "x": 741,
                        "y": 416
                    },
                    {
                        "x": 740,
                        "y": 417
                    },
                    {
                        "x": 740,
                        "y": 420
                    },
                    {
                        "x": 739,
                        "y": 421
                    },
                    {
                        "x": 739,
                        "y": 425
                    },
                    {
                        "x": 738,
                        "y": 426
                    },
                    {
                        "x": 738,
                        "y": 453
                    },
                    {
                        "x": 739,
                        "y": 454
                    },
                    {
                        "x": 739,
                        "y": 457
                    },
                    {
                        "x": 740,
                        "y": 458
                    },
                    {
                        "x": 740,
                        "y": 459
                    },
                    {
                        "x": 741,
                        "y": 460
                    },
                    {
                        "x": 741,
                        "y": 462
                    },
                    {
                        "x": 742,
                        "y": 463
                    },
                    {
                        "x": 742,
                        "y": 464
                    },
                    {
                        "x": 743,
                        "y": 465
                    },
                    {
                        "x": 743,
                        "y": 466
                    },
                    {
                        "x": 744,
                        "y": 467
                    },
                    {
                        "x": 744,
                        "y": 469
                    },
                    {
                        "x": 745,
                        "y": 470
                    },
                    {
                        "x": 745,
                        "y": 472
                    },
                    {
                        "x": 746,
                        "y": 473
                    },
                    {
                        "x": 746,
                        "y": 475
                    },
                    {
                        "x": 747,
                        "y": 476
                    },
                    {
                        "x": 747,
                        "y": 479
                    },
                    {
                        "x": 748,
                        "y": 480
                    },
                    {
                        "x": 748,
                        "y": 483
                    },
                    {
                        "x": 749,
                        "y": 484
                    },
                    {
                        "x": 749,
                        "y": 486
                    },
                    {
                        "x": 750,
                        "y": 487
                    },
                    {
                        "x": 750,
                        "y": 493
                    },
                    {
                        "x": 751,
                        "y": 494
                    },
                    {
                        "x": 751,
                        "y": 498
                    },
                    {
                        "x": 752,
                        "y": 499
                    },
                    {
                        "x": 752,
                        "y": 506
                    },
                    {
                        "x": 753,
                        "y": 507
                    },
                    {
                        "x": 753,
                        "y": 517
                    },
                    {
                        "x": 754,
                        "y": 518
                    },
                    {
                        "x": 754,
                        "y": 520
                    },
                    {
                        "x": 753,
                        "y": 521
                    },
                    {
                        "x": 753,
                        "y": 540
                    },
                    {
                        "x": 752,
                        "y": 541
                    },
                    {
                        "x": 752,
                        "y": 546
                    },
                    {
                        "x": 751,
                        "y": 547
                    },
                    {
                        "x": 751,
                        "y": 550
                    },
                    {
                        "x": 750,
                        "y": 551
                    },
                    {
                        "x": 750,
                        "y": 553
                    },
                    {
                        "x": 749,
                        "y": 554
                    },
                    {
                        "x": 749,
                        "y": 555
                    },
                    {
                        "x": 748,
                        "y": 556
                    },
                    {
                        "x": 748,
                        "y": 557
                    },
                    {
                        "x": 747,
                        "y": 558
                    },
                    {
                        "x": 747,
                        "y": 559
                    },
                    {
                        "x": 746,
                        "y": 560
                    },
                    {
                        "x": 746,
                        "y": 561
                    },
                    {
                        "x": 745,
                        "y": 562
                    },
                    {
                        "x": 745,
                        "y": 563
                    },
                    {
                        "x": 743,
                        "y": 565
                    },
                    {
                        "x": 743,
                        "y": 566
                    },
                    {
                        "x": 742,
                        "y": 567
                    },
                    {
                        "x": 742,
                        "y": 568
                    },
                    {
                        "x": 740,
                        "y": 570
                    },
                    {
                        "x": 740,
                        "y": 572
                    },
                    {
                        "x": 739,
                        "y": 573
                    },
                    {
                        "x": 739,
                        "y": 574
                    },
                    {
                        "x": 738,
                        "y": 575
                    },
                    {
                        "x": 738,
                        "y": 576
                    },
                    {
                        "x": 737,
                        "y": 577
                    },
                    {
                        "x": 737,
                        "y": 578
                    },
                    {
                        "x": 736,
                        "y": 579
                    },
                    {
                        "x": 736,
                        "y": 581
                    },
                    {
                        "x": 735,
                        "y": 582
                    },
                    {
                        "x": 735,
                        "y": 584
                    },
                    {
                        "x": 734,
                        "y": 585
                    },
                    {
                        "x": 734,
                        "y": 588
                    },
                    {
                        "x": 733,
                        "y": 589
                    },
                    {
                        "x": 733,
                        "y": 593
                    },
                    {
                        "x": 732,
                        "y": 594
                    },
                    {
                        "x": 732,
                        "y": 623
                    },
                    {
                        "x": 733,
                        "y": 624
                    },
                    {
                        "x": 733,
                        "y": 628
                    },
                    {
                        "x": 734,
                        "y": 629
                    },
                    {
                        "x": 734,
                        "y": 633
                    },
                    {
                        "x": 735,
                        "y": 634
                    },
                    {
                        "x": 735,
                        "y": 636
                    },
                    {
                        "x": 736,
                        "y": 637
                    },
                    {
                        "x": 736,
                        "y": 638
                    },
                    {
                        "x": 737,
                        "y": 639
                    },
                    {
                        "x": 737,
                        "y": 641
                    },
                    {
                        "x": 738,
                        "y": 642
                    },
                    {
                        "x": 738,
                        "y": 643
                    },
                    {
                        "x": 739,
                        "y": 644
                    },
                    {
                        "x": 739,
                        "y": 646
                    },
                    {
                        "x": 740,
                        "y": 647
                    },
                    {
                        "x": 740,
                        "y": 648
                    },
                    {
                        "x": 741,
                        "y": 649
                    },
                    {
                        "x": 741,
                        "y": 650
                    },
                    {
                        "x": 742,
                        "y": 651
                    },
                    {
                        "x": 742,
                        "y": 652
                    },
                    {
                        "x": 743,
                        "y": 653
                    },
                    {
                        "x": 743,
                        "y": 654
                    },
                    {
                        "x": 744,
                        "y": 655
                    },
                    {
                        "x": 744,
                        "y": 656
                    },
                    {
                        "x": 745,
                        "y": 657
                    },
                    {
                        "x": 745,
                        "y": 658
                    },
                    {
                        "x": 747,
                        "y": 660
                    },
                    {
                        "x": 747,
                        "y": 661
                    },
                    {
                        "x": 748,
                        "y": 662
                    },
                    {
                        "x": 748,
                        "y": 663
                    },
                    {
                        "x": 750,
                        "y": 665
                    },
                    {
                        "x": 750,
                        "y": 666
                    },
                    {
                        "x": 751,
                        "y": 667
                    },
                    {
                        "x": 751,
                        "y": 668
                    },
                    {
                        "x": 755,
                        "y": 672
                    },
                    {
                        "x": 755,
                        "y": 673
                    },
                    {
                        "x": 766,
                        "y": 684
                    },
                    {
                        "x": 767,
                        "y": 684
                    },
                    {
                        "x": 770,
                        "y": 687
                    },
                    {
                        "x": 771,
                        "y": 687
                    },
                    {
                        "x": 773,
                        "y": 689
                    },
                    {
                        "x": 774,
                        "y": 689
                    },
                    {
                        "x": 776,
                        "y": 691
                    },
                    {
                        "x": 777,
                        "y": 691
                    },
                    {
                        "x": 778,
                        "y": 692
                    },
                    {
                        "x": 779,
                        "y": 692
                    },
                    {
                        "x": 780,
                        "y": 693
                    },
                    {
                        "x": 781,
                        "y": 693
                    },
                    {
                        "x": 782,
                        "y": 694
                    },
                    {
                        "x": 784,
                        "y": 694
                    },
                    {
                        "x": 785,
                        "y": 695
                    },
                    {
                        "x": 788,
                        "y": 695
                    },
                    {
                        "x": 789,
                        "y": 696
                    },
                    {
                        "x": 806,
                        "y": 696
                    },
                    {
                        "x": 807,
                        "y": 695
                    },
                    {
                        "x": 817,
                        "y": 695
                    },
                    {
                        "x": 818,
                        "y": 696
                    },
                    {
                        "x": 844,
                        "y": 696
                    },
                    {
                        "x": 845,
                        "y": 695
                    },
                    {
                        "x": 847,
                        "y": 695
                    },
                    {
                        "x": 848,
                        "y": 694
                    },
                    {
                        "x": 849,
                        "y": 694
                    },
                    {
                        "x": 850,
                        "y": 693
                    },
                    {
                        "x": 851,
                        "y": 693
                    },
                    {
                        "x": 852,
                        "y": 692
                    },
                    {
                        "x": 853,
                        "y": 692
                    },
                    {
                        "x": 854,
                        "y": 691
                    },
                    {
                        "x": 855,
                        "y": 691
                    },
                    {
                        "x": 856,
                        "y": 690
                    },
                    {
                        "x": 857,
                        "y": 690
                    },
                    {
                        "x": 858,
                        "y": 689
                    },
                    {
                        "x": 859,
                        "y": 689
                    },
                    {
                        "x": 861,
                        "y": 687
                    },
                    {
                        "x": 862,
                        "y": 687
                    },
                    {
                        "x": 865,
                        "y": 684
                    },
                    {
                        "x": 866,
                        "y": 684
                    },
                    {
                        "x": 876,
                        "y": 674
                    },
                    {
                        "x": 876,
                        "y": 673
                    },
                    {
                        "x": 879,
                        "y": 670
                    },
                    {
                        "x": 879,
                        "y": 669
                    },
                    {
                        "x": 882,
                        "y": 666
                    },
                    {
                        "x": 882,
                        "y": 665
                    },
                    {
                        "x": 884,
                        "y": 663
                    },
                    {
                        "x": 884,
                        "y": 662
                    },
                    {
                        "x": 886,
                        "y": 660
                    },
                    {
                        "x": 886,
                        "y": 659
                    },
                    {
                        "x": 888,
                        "y": 657
                    },
                    {
                        "x": 888,
                        "y": 656
                    },
                    {
                        "x": 889,
                        "y": 655
                    },
                    {
                        "x": 889,
                        "y": 654
                    },
                    {
                        "x": 890,
                        "y": 653
                    },
                    {
                        "x": 890,
                        "y": 652
                    },
                    {
                        "x": 891,
                        "y": 651
                    },
                    {
                        "x": 891,
                        "y": 650
                    },
                    {
                        "x": 892,
                        "y": 649
                    },
                    {
                        "x": 892,
                        "y": 648
                    },
                    {
                        "x": 894,
                        "y": 646
                    },
                    {
                        "x": 894,
                        "y": 644
                    },
                    {
                        "x": 895,
                        "y": 643
                    },
                    {
                        "x": 895,
                        "y": 641
                    },
                    {
                        "x": 896,
                        "y": 640
                    },
                    {
                        "x": 896,
                        "y": 639
                    },
                    {
                        "x": 897,
                        "y": 638
                    },
                    {
                        "x": 897,
                        "y": 635
                    },
                    {
                        "x": 898,
                        "y": 634
                    },
                    {
                        "x": 898,
                        "y": 631
                    },
                    {
                        "x": 899,
                        "y": 630
                    },
                    {
                        "x": 899,
                        "y": 628
                    },
                    {
                        "x": 900,
                        "y": 627
                    },
                    {
                        "x": 900,
                        "y": 623
                    },
                    {
                        "x": 901,
                        "y": 622
                    },
                    {
                        "x": 901,
                        "y": 596
                    },
                    {
                        "x": 900,
                        "y": 595
                    },
                    {
                        "x": 900,
                        "y": 591
                    },
                    {
                        "x": 899,
                        "y": 590
                    },
                    {
                        "x": 899,
                        "y": 588
                    },
                    {
                        "x": 898,
                        "y": 587
                    },
                    {
                        "x": 898,
                        "y": 584
                    },
                    {
                        "x": 897,
                        "y": 583
                    },
                    {
                        "x": 897,
                        "y": 581
                    },
                    {
                        "x": 896,
                        "y": 580
                    },
                    {
                        "x": 896,
                        "y": 579
                    },
                    {
                        "x": 895,
                        "y": 578
                    },
                    {
                        "x": 895,
                        "y": 576
                    },
                    {
                        "x": 894,
                        "y": 575
                    },
                    {
                        "x": 894,
                        "y": 574
                    },
                    {
                        "x": 893,
                        "y": 573
                    },
                    {
                        "x": 893,
                        "y": 571
                    },
                    {
                        "x": 892,
                        "y": 570
                    },
                    {
                        "x": 892,
                        "y": 569
                    },
                    {
                        "x": 891,
                        "y": 568
                    },
                    {
                        "x": 891,
                        "y": 567
                    },
                    {
                        "x": 890,
                        "y": 566
                    },
                    {
                        "x": 890,
                        "y": 565
                    },
                    {
                        "x": 889,
                        "y": 564
                    },
                    {
                        "x": 889,
                        "y": 563
                    },
                    {
                        "x": 888,
                        "y": 562
                    },
                    {
                        "x": 888,
                        "y": 561
                    },
                    {
                        "x": 886,
                        "y": 559
                    },
                    {
                        "x": 886,
                        "y": 558
                    },
                    {
                        "x": 885,
                        "y": 557
                    },
                    {
                        "x": 885,
                        "y": 556
                    },
                    {
                        "x": 884,
                        "y": 555
                    },
                    {
                        "x": 884,
                        "y": 553
                    },
                    {
                        "x": 883,
                        "y": 552
                    },
                    {
                        "x": 883,
                        "y": 550
                    },
                    {
                        "x": 882,
                        "y": 549
                    },
                    {
                        "x": 882,
                        "y": 544
                    },
                    {
                        "x": 881,
                        "y": 543
                    },
                    {
                        "x": 881,
                        "y": 530
                    },
                    {
                        "x": 880,
                        "y": 529
                    },
                    {
                        "x": 880,
                        "y": 527
                    },
                    {
                        "x": 881,
                        "y": 526
                    },
                    {
                        "x": 881,
                        "y": 512
                    },
                    {
                        "x": 882,
                        "y": 511
                    },
                    {
                        "x": 882,
                        "y": 506
                    },
                    {
                        "x": 883,
                        "y": 505
                    },
                    {
                        "x": 883,
                        "y": 498
                    },
                    {
                        "x": 884,
                        "y": 497
                    },
                    {
                        "x": 884,
                        "y": 493
                    },
                    {
                        "x": 885,
                        "y": 492
                    },
                    {
                        "x": 885,
                        "y": 488
                    },
                    {
                        "x": 886,
                        "y": 487
                    },
                    {
                        "x": 886,
                        "y": 484
                    },
                    {
                        "x": 887,
                        "y": 483
                    },
                    {
                        "x": 887,
                        "y": 481
                    },
                    {
                        "x": 888,
                        "y": 480
                    },
                    {
                        "x": 888,
                        "y": 478
                    },
                    {
                        "x": 889,
                        "y": 477
                    },
                    {
                        "x": 889,
                        "y": 475
                    },
                    {
                        "x": 890,
                        "y": 474
                    },
                    {
                        "x": 890,
                        "y": 472
                    },
                    {
                        "x": 891,
                        "y": 471
                    },
                    {
                        "x": 891,
                        "y": 469
                    },
                    {
                        "x": 892,
                        "y": 468
                    },
                    {
                        "x": 892,
                        "y": 466
                    },
                    {
                        "x": 893,
                        "y": 465
                    },
                    {
                        "x": 893,
                        "y": 464
                    },
                    {
                        "x": 894,
                        "y": 463
                    },
                    {
                        "x": 894,
                        "y": 462
                    },
                    {
                        "x": 895,
                        "y": 461
                    },
                    {
                        "x": 895,
                        "y": 459
                    },
                    {
                        "x": 896,
                        "y": 458
                    },
                    {
                        "x": 896,
                        "y": 456
                    },
                    {
                        "x": 897,
                        "y": 455
                    },
                    {
                        "x": 897,
                        "y": 452
                    },
                    {
                        "x": 898,
                        "y": 451
                    },
                    {
                        "x": 898,
                        "y": 429
                    },
                    {
                        "x": 897,
                        "y": 428
                    },
                    {
                        "x": 897,
                        "y": 423
                    },
                    {
                        "x": 896,
                        "y": 422
                    },
                    {
                        "x": 896,
                        "y": 419
                    },
                    {
                        "x": 895,
                        "y": 418
                    },
                    {
                        "x": 895,
                        "y": 415
                    },
                    {
                        "x": 894,
                        "y": 414
                    },
                    {
                        "x": 894,
                        "y": 411
                    },
                    {
                        "x": 893,
                        "y": 410
                    },
                    {
                        "x": 893,
                        "y": 409
                    },
                    {
                        "x": 892,
                        "y": 408
                    },
                    {
                        "x": 892,
                        "y": 406
                    },
                    {
                        "x": 891,
                        "y": 405
                    },
                    {
                        "x": 891,
                        "y": 403
                    },
                    {
                        "x": 890,
                        "y": 402
                    },
                    {
                        "x": 890,
                        "y": 401
                    },
                    {
                        "x": 889,
                        "y": 400
                    },
                    {
                        "x": 889,
                        "y": 398
                    },
                    {
                        "x": 888,
                        "y": 397
                    },
                    {
                        "x": 888,
                        "y": 396
                    },
                    {
                        "x": 887,
                        "y": 395
                    },
                    {
                        "x": 887,
                        "y": 394
                    },
                    {
                        "x": 885,
                        "y": 392
                    },
                    {
                        "x": 885,
                        "y": 391
                    },
                    {
                        "x": 884,
                        "y": 390
                    },
                    {
                        "x": 884,
                        "y": 389
                    },
                    {
                        "x": 875,
                        "y": 380
                    },
                    {
                        "x": 874,
                        "y": 380
                    },
                    {
                        "x": 871,
                        "y": 377
                    },
                    {
                        "x": 870,
                        "y": 377
                    },
                    {
                        "x": 867,
                        "y": 374
                    },
                    {
                        "x": 866,
                        "y": 374
                    },
                    {
                        "x": 865,
                        "y": 373
                    },
                    {
                        "x": 864,
                        "y": 373
                    },
                    {
                        "x": 862,
                        "y": 371
                    },
                    {
                        "x": 861,
                        "y": 371
                    },
                    {
                        "x": 860,
                        "y": 370
                    },
                    {
                        "x": 859,
                        "y": 370
                    },
                    {
                        "x": 858,
                        "y": 369
                    },
                    {
                        "x": 857,
                        "y": 369
                    },
                    {
                        "x": 855,
                        "y": 367
                    },
                    {
                        "x": 853,
                        "y": 367
                    },
                    {
                        "x": 852,
                        "y": 366
                    },
                    {
                        "x": 850,
                        "y": 366
                    },
                    {
                        "x": 849,
                        "y": 365
                    },
                    {
                        "x": 848,
                        "y": 365
                    },
                    {
                        "x": 847,
                        "y": 364
                    },
                    {
                        "x": 845,
                        "y": 364
                    },
                    {
                        "x": 844,
                        "y": 363
                    },
                    {
                        "x": 841,
                        "y": 363
                    },
                    {
                        "x": 840,
                        "y": 362
                    },
                    {
                        "x": 837,
                        "y": 362
                    },
                    {
                        "x": 836,
                        "y": 361
                    },
                    {
                        "x": 831,
                        "y": 361
                    },
                    {
                        "x": 830,
                        "y": 360
                    }
                ],
                "edgeSensitivity": 213,
                "maxShapeDistance": 0.58,
                "minTemplateScore": 0.25,
                "modelUseEdges": false,
                "searchRoi": {
                    "height": 368,
                    "width": 207,
                    "x": 714,
                    "y": 350
                },
                "templateImagePath": "assets/CAM01_surface_model_template.png",
                "useConvexHull": false
            }
        }
    }
}
